CHANGELOG.md
LICENSE
YahooRequests/__init__.py
YahooRequests/yahoorequests.py
yahoorequests-1.11.dist-info/LICENSE
yahoorequests-1.11.dist-info/METADATA
yahoorequests-1.11.dist-info/WHEEL
yahoorequests-1.11.dist-info/entry_points.txt
yahoorequests-1.11.dist-info/RECORD
