Metadata-Version: 2.1
Name: YahooRequests
Version: 1.11
Summary: A simple Python library for getting stock prices and company names from Yahoo Finance.
Home-page: https://github.com/TheodorGajhede/YahooRequests
License: MIT
Keywords: Stocks,Yahoo,Finance
Author: Theodor Gajhede
Author-email: theodorgajhede@gmail.com
Classifier: License :: OSI Approved :: MIT License
Classifier: Programming Language :: Python :: 2
Classifier: Programming Language :: Python :: 2.7
Classifier: Programming Language :: Python :: 3
Classifier: Programming Language :: Python :: 3.4
Classifier: Programming Language :: Python :: 3.5
Classifier: Programming Language :: Python :: 3.6
Classifier: Programming Language :: Python :: 3.7
Classifier: Programming Language :: Python :: 3.8
Classifier: Programming Language :: Python :: 3.9
Classifier: Programming Language :: Python :: 3.10
Classifier: Programming Language :: Python :: 3.11
Classifier: Programming Language :: Python :: 3.12
Requires-Dist: datetime (>=1.5,<2.0)
Requires-Dist: httpstatus (>=0.9.1,<0.10.0)
Requires-Dist: newsapi-python (>=2.5,<3.0)
Requires-Dist: requests (>=2.26.0,<3.0.0)
Requires-Dist: tabulate (>=0.8.10,<0.9.0)
Project-URL: Repository, https://github.com/TheodorGajhede/YahooRequests.git
